science_parse_api/__init__.py
science_parse_api/_nbdev.py
science_parse_api/api.py
science_parse_api/test_helper.py
science_parse_api-1.0.1.dist-info/LICENSE
science_parse_api-1.0.1.dist-info/METADATA
science_parse_api-1.0.1.dist-info/WHEEL
science_parse_api-1.0.1.dist-info/top_level.txt
science_parse_api-1.0.1.dist-info/RECORD
