Metadata-Version: 2.1
Name: science-parse-api
Version: 1.0.1
Summary: Python API for Science Parse
Home-page: https://github.com/UCREL/science_parse_py_api/tree/master/
Author: Andrew Moore
Author-email: andrew.p.moore94@gmail.com
License: Apache Software License 2.0
Keywords: natural-language-processing nlp
Platform: UNKNOWN
Classifier: Development Status :: 5 - Production/Stable
Classifier: Intended Audience :: Developers
Classifier: Natural Language :: English
Classifier: Programming Language :: Python :: 3.6
Classifier: Programming Language :: Python :: 3.7
Classifier: Programming Language :: Python :: 3.8
Classifier: License :: OSI Approved :: Apache Software License
Requires-Python: >=3.6
Requires-Dist: requests
Provides-Extra: dev
Requires-Dist: nbdev ; extra == 'dev'
Requires-Dist: responses ; extra == 'dev'
Requires-Dist: pytest ; extra == 'dev'
Requires-Dist: pytest-cov ; extra == 'dev'
Requires-Dist: twine ; extra == 'dev'
